<?xml version="1.0" encoding="UTF-8"?>
<beans xmlns="http://www.springframework.org/schema/beans"
xmlns:context="http://www.springframework.org/schema/context"
	xmlns:xsi="http://www.w3.org/2001/XMLSchema-instance" xmlns:aop="http://www.springframework.org/schema/aop"
	xmlns:tx="http://www.springframework.org/schema/tx"
	xsi:schemaLocation="http://www.springframework.org/schema/beans http://www.springframework.org/schema/beans/spring-beans.xsd 
http://www.springframework.org/schema/aop http://www.springframework.org/schema/aop/spring-aop.xsd
http://www.springframework.org/schema/tx http://www.springframework.org/schema/tx/spring-tx.xsd http://www.springframework.org/schema/context
	http://www.springframework.org/schema/context/spring-context.xsd">
	
	<bean id="networksJaxb2UnmarshallerId" class="org.springframework.oxm.jaxb.Jaxb2Marshaller">
        <property name="lazyInit" value="true"/>
		<property name="classesToBeBound">
            <list>
                <value>io.delimeat.core.networks.Networks</value>
                <value>io.delimeat.core.networks.Network</value>            
            </list>
        </property>
        <!-- 
        <property name="jaxbContextProperties">
        	<map> 
        		<entry key="eclipselink-oxm-xml">
        		<value type="java.io.InputStream">classpath://META-INF/oxm/networks-oxm.xml</value>
        		</entry>
        	</map>
        </property>
        !-->
    </bean>
    
    <bean id="networksUnmarshallerId" class="javax.xml.bind.Unmarshaller" factory-bean="networksJaxb2UnmarshallerId" factory-method="createUnmarshaller" />
	
	<bean id="networksDaoId" class="io.delimeat.core.networks.JaxbNetworksDao_Impl">
		<property name="unmarshaller" ref="networksUnmarshallerId" />
		<property name="urlHandler" ref="urlHandlerId" />
		<property name="uri" value ="classpath://META-INF/tvdb-networks.xml"/>
	</bean>

</beans>