<?xml version="1.0"?>
<xml-bindings xmlns="http://www.eclipse.org/eclipselink/xsds/persistence/oxm"
	xmlns:xsi="http://www.w3.org/2001/XMLSchema-instance" xmlns:xs="http://www.w3.org/2001/XMLSchema"
	xml-accessor-type="NONE" package-name="io.delimeat.core.guide"
	xml-mapping-metadata-complete="true">

	<java-types>

      <java-type name="GuideError">
			<xml-root-element/>
			<java-attributes>
				<xml-element java-attribute="message" name="name" />
			</java-attributes>
		</java-type>
     
		<java-type name="GuideSearchResult">
			<xml-root-element/>
			<java-attributes>
				<xml-element java-attribute="description" xml-path="show/summary/text()">
					<xml-java-type-adapter value="io.delimeat.util.jaxb.JaxbStringAdapter" />
				</xml-element>
				<xml-element java-attribute="firstAired" xml-path="show/premiered/text()">
					<xml-java-type-adapter value="io.delimeat.util.jaxb.TvdbDateAdapter" />
				</xml-element>
				<xml-element java-attribute="guideIds" name="show/id/text()">
					<xml-java-type-adapter
						value="io.delimeat.util.jaxb.TvMazeIdentifierAdapter" />
				</xml-element>
				<xml-element java-attribute="guideIds"
					xml-path="show/externals/thetvdb/text()">
					<xml-java-type-adapter
						value="io.delimeat.util.jaxb.TvdbIdentifierAdapter" />
				</xml-element>
				<xml-element java-attribute="guideIds"
					xml-path="show/externals/tvrage/text()">
					<xml-java-type-adapter
						value="io.delimeat.util.jaxb.TvRageIdentifierAdapter" />
				</xml-element>
				<xml-element java-attribute="title" name="show/name/text()" />
			</java-attributes>
		</java-type>

		<java-type name="GuideInfo">
			<xml-root-element/>
			<java-attributes>
				<xml-element java-attribute="guideIds" name="id">
					<xml-java-type-adapter
						value="io.delimeat.util.jaxb.TvMazeIdentifierAdapter" />
				</xml-element>	
				<xml-element java-attribute="guideIds" xml-path="externals/thetvdb/text()" type="java.lang.Integer">
					<xml-java-type-adapter
						value="io.delimeat.util.jaxb.TvdbIdentifierAdapter" />
				</xml-element>
				<xml-element java-attribute="guideIds"  xml-path="externals/tvrage/text()"  type="java.lang.Integer" >
					<xml-java-type-adapter
						value="io.delimeat.util.jaxb.TvRageIdentifierAdapter" />
				</xml-element>
				<xml-element java-attribute="title" name="name" />
				<xml-element java-attribute="description" name="summary">
					<xml-java-type-adapter value="io.delimeat.util.jaxb.JaxbStringAdapter" />
				</xml-element>
				<xml-element java-attribute="runningTime" name="runtime" />
				<xml-element java-attribute="timezone" xml-path="network/country/timezone/text()" />
				<xml-element java-attribute="airDays" xml-path="schedule/days/text()" xml-list="true">
					<xml-java-type-adapter value="io.delimeat.util.jaxb.TvMazeAiringDayAdapter" />
				</xml-element>

				<xml-element java-attribute="airing" name="status">
					<xml-java-type-adapter
						value="io.delimeat.util.jaxb.TvdbAiringStatusAdapter" />
				</xml-element>
				<xml-element java-attribute="airTime" xml-path="schedule/time/text()">
					<xml-java-type-adapter value="io.delimeat.util.jaxb.TvdbAirTimeAdapter" />
				</xml-element>
				<xml-element java-attribute="genres" name="genres"
					xml-list="true" />
			</java-attributes>
		</java-type>

		<java-type name="GuideEpisode">
			<xml-root-element/>
			<java-attributes>
				<xml-element java-attribute="airDate" name="airdate">
					<xml-java-type-adapter value="io.delimeat.util.jaxb.TvdbDateAdapter" />
				</xml-element>
				<xml-element java-attribute="seasonNum" name="season" />
				<xml-element java-attribute="episodeNum" name="number" />
				<xml-element java-attribute="productionNum" name="absoluteNumber" />
				<xml-element java-attribute="title" name="name" />
			</java-attributes>
		</java-type>

	</java-types>
	
</xml-bindings>